{
  "timestamp": "2026-05-19T20:00:23.704198",
  "summary": {
    "total_ui_issues": 5,
    "high": 1,
    "medium": 1,
    "low": 3,
    "observations": 5
  },
  "ui_issues": [
    {
      "page": "/login",
      "severity": "high",
      "issue": "Auth error: Locator.count: Unexpected token \"=\" while parsing css selector \"button:has-text(\"Password\"), [role=\"tab\"]:has-text(\"Password\"), text=\"Password\"\". Did you mean to CSS.escape it?"
    },
    {
      "page": "mobile",
      "severity": "medium",
      "issue": "Horizontal overflow detected"
    },
    {
      "page": "cards",
      "severity": "low",
      "issue": "Error: Page.evaluate: TypeError: cards.slice is not a function\n    at eval (eval at evaluate (:302:30), <anonymous>:4:23)\n    at UtilityScript.evaluate (<anonymous>:309:18)\n    at UtilityScript.<anonymous> (<anonymous>:1:44)"
    },
    {
      "page": "forms",
      "severity": "low",
      "issue": "Error: Page.evaluate: TypeError: inputs.slice is not a function\n    at eval (eval at evaluate (:302:30), <anonymous>:4:24)\n    at UtilityScript.evaluate (<anonymous>:309:18)\n    at UtilityScript.<anonymous> (<anonymous>:1:44)"
    },
    {
      "page": "polish",
      "severity": "low",
      "issue": "Error: Page.evaluate: TypeError: cards.slice is not a function\n    at eval (eval at evaluate (:302:30), <anonymous>:5:23)\n    at UtilityScript.evaluate (<anonymous>:309:18)\n    at UtilityScript.<anonymous> (<anonymous>:1:44)"
    }
  ],
  "ui_observations": [
    {
      "element": "Hero heading",
      "text": "Find your flatmate, not a nightmare"
    },
    {
      "page": "/discover",
      "observation": "14 low-res images"
    },
    {
      "page": "mobile",
      "observation": "Bottom nav not found"
    },
    {
      "page": "icons",
      "observation": "100 icons without labels"
    },
    {
      "page": "loading",
      "observation": "No skeleton loaders visible"
    }
  ]
}